choicemodels/__init__.py
choicemodels/mnl.py
choicemodels/tools/__init__.py
choicemodels/tools/distancematrix.py
choicemodels/tools/mergedchoicetable.py
choicemodels/tools/pmat.py
choicemodels/tools/simulation.py
choicemodels-0.2.2.dist-info/DESCRIPTION.rst
choicemodels-0.2.2.dist-info/METADATA
choicemodels-0.2.2.dist-info/RECORD
choicemodels-0.2.2.dist-info/WHEEL
choicemodels-0.2.2.dist-info/metadata.json
choicemodels-0.2.2.dist-info/top_level.txt
