Metadata-Version: 2.0
Name: choicemodels
Version: 0.2.2
Summary: Tools for discrete choice estimation
Home-page: https://github.com/udst/choicemodels
Author: UDST
Author-email: UNKNOWN
License: UNKNOWN
Platform: UNKNOWN
Classifier: Intended Audience :: Science/Research
Classifier: Topic :: Scientific/Engineering :: Information Analysis
Classifier: Programming Language :: Python :: 2
Classifier: Programming Language :: Python :: 2.7
Classifier: Programming Language :: Python :: 3
Classifier: Programming Language :: Python :: 3.5
Classifier: Programming Language :: Python :: 3.6
Classifier: Programming Language :: Python :: 3.7
Classifier: Programming Language :: Python :: 3.8
Classifier: License :: OSI Approved :: BSD License
Requires-Dist: numpy (>=1.14)
Requires-Dist: pandas (>=0.23)
Requires-Dist: patsy (>=0.5)
Requires-Dist: pylogit (>=0.2.2)
Requires-Dist: scipy (>=1.0)
Requires-Dist: statsmodels (>=0.8,<0.11); python_version < "3.6"
Requires-Dist: statsmodels (>=0.8); python_version >= "3.6"
